cents/config/config.yaml
cents/config/dataset/default.yaml
cents/config/dataset/pecanstreet.yaml
cents/config/evaluator/default.yaml
cents/config/model/acgan.yaml
cents/config/model/diffusion_ts.yaml
cents/config/trainer/acgan.yaml
cents/config/trainer/diffusion_ts.yaml
cents/config/trainer/normalizer.yaml
cents/data_generator.py
cents/datasets/pecanstreet.py
cents/datasets/timeseries_dataset.py
cents/datasets/utils.py
cents/eval/discriminative_score.py
cents/eval/eval.py
cents/eval/eval_metrics.py
cents/eval/eval_utils.py
cents/eval/predictive_score.py
cents/eval/t2vec/dilated_conv.py
cents/eval/t2vec/encoder.py
cents/eval/t2vec/t2vec.py
cents/models/__init__.py
cents/models/acgan.py
cents/models/base.py
cents/models/context.py
cents/models/diffusion_ts.py
cents/models/model_utils.py
cents/models/normalizer.py
cents/models/registry.py
cents/trainer.py
cents/utils/utils.py
cents_ml-1.0.1.dist-info/AUTHORS.rst
cents_ml-1.0.1.dist-info/LICENSE
cents_ml-1.0.1.dist-info/METADATA
cents_ml-1.0.1.dist-info/WHEEL
cents_ml-1.0.1.dist-info/RECORD
