Metadata-Version: 2.3
Name: cents-ml
Version: 1.0.1
Summary: A library for generating contextual timeseries data.
License: MIT
Author: Michael Fuest
Requires-Python: >=3.9,<4.0
Classifier: License :: OSI Approved :: MIT License
Classifier: Programming Language :: Python :: 3
Classifier: Programming Language :: Python :: 3.9
Classifier: Programming Language :: Python :: 3.10
Classifier: Programming Language :: Python :: 3.11
Classifier: Programming Language :: Python :: 3.12
Classifier: Programming Language :: Python :: 3.13
Requires-Dist: accelerate (>=1.2.0,<2.0.0)
Requires-Dist: autoflake (>=2.3.1,<3.0.0)
Requires-Dist: black (>=24.10.0,<25.0.0)
Requires-Dist: botocore (>=1.36.24,<2.0.0)
Requires-Dist: dtaidistance (>=2.3.12,<3.0.0)
Requires-Dist: einops (>=0.8.0,<0.9.0)
Requires-Dist: huggingface-hub (>=0.32.0,<0.33.0)
Requires-Dist: hydra-core (>=1.3.2,<2.0.0)
Requires-Dist: ipykernel (>=6.29.5,<7.0.0)
Requires-Dist: isort (>=5.13.2,<6.0.0)
Requires-Dist: jupyter (>=1.1.1,<2.0.0)
Requires-Dist: matplotlib (>=3.9.4,<4.0.0)
Requires-Dist: mypy (>=1.13.0,<2.0.0)
Requires-Dist: numpy (>=2.0.0,<3.0.0)
Requires-Dist: omegaconf (>=2.3.0,<3.0.0)
Requires-Dist: pandas (>=2.2.3,<3.0.0)
Requires-Dist: pre-commit (>=4.0.1,<5.0.0)
Requires-Dist: pytest (>=8.3.4,<9.0.0)
Requires-Dist: pytest-cov (>=6.0.0,<7.0.0)
Requires-Dist: pytorch-lightning (>=2.4.0,<3.0.0)
Requires-Dist: pyyaml (>=6.0.2,<7.0.0)
Requires-Dist: scikit-learn (>=1.6.0,<2.0.0)
Requires-Dist: seaborn (>=0.13.2,<0.14.0)
Requires-Dist: sentencepiece (>=0.2.0,<0.3.0)
Requires-Dist: tiktoken (>=0.8.0,<0.9.0)
Requires-Dist: torch (==2.6.0)
Requires-Dist: torchaudio (==2.6.0)
Requires-Dist: torchvision (>=0.21.0,<0.22.0)
Requires-Dist: transformers (>=4.48.0,<5.0.0)
Requires-Dist: wandb (>=0.19.6,<0.20.0)
